{
    "MIGHTE-Nsemble": {
        "target_end_date": [
            "2026-04-11",
            "2026-04-18",
            "2026-04-25",
            "2026-05-02"
        ],
        "q0.025": [
            3.9581613830849065,
            0.0,
            0.0,
            4.681720314903986
        ],
        "q0.25": [
            17.078679798501422,
            2.367409709154853,
            7.141633825552471,
            14.710301569677368
        ],
        "q0.5": [
            26.135147992402125,
            10.882492785768816,
            13.921892154915248,
            24.813253022878882
        ],
        "q0.75": [
            38.079948778204646,
            20.49004785720189,
            22.177110727482155,
            42.16319950980217
        ],
        "q0.975": [
            85.54525716001072,
            54.95604981603652,
            47.8258801713423,
            137.1880820032205
        ]
    },
    "NAU-epymorph": {
        "target_end_date": [
            "2026-04-04",
            "2026-04-11",
            "2026-04-18",
            "2026-04-25",
            "2026-05-02"
        ],
        "q0.025": [
            44.0,
            32.0,
            18.0,
            10.0,
            6.0
        ],
        "q0.25": [
            51.0,
            41.0,
            26.0,
            17.0,
            12.0
        ],
        "q0.5": [
            56.0,
            46.0,
            31.0,
            22.0,
            17.0
        ],
        "q0.75": [
            61.0,
            52.0,
            37.0,
            29.0,
            23.0
        ],
        "q0.975": [
            70.0,
            65.0,
            51.0,
            45.0,
            44.0
        ]
    },
    "UI_CompEpi-EpiGen": {
        "target_end_date": [
            "2026-04-11",
            "2026-04-18",
            "2026-04-25",
            "2026-05-02"
        ],
        "q0.025": [
            0.0,
            0.0,
            0.0,
            0.0
        ],
        "q0.25": [
            0.0,
            0.0,
            0.0,
            0.0
        ],
        "q0.5": [
            20.0,
            16.0,
            14.0,
            23.0
        ],
        "q0.75": [
            43.0,
            52.0,
            55.0,
            66.0
        ],
        "q0.975": [
            94.0,
            112.0,
            129.0,
            139.0
        ]
    },
    "FluSight-ensemble": {
        "target_end_date": [
            "2026-04-11",
            "2026-04-18",
            "2026-04-25",
            "2026-05-02"
        ],
        "q0.025": [
            4.0,
            0.0,
            0.0,
            0.0
        ],
        "q0.25": [
            17.0,
            13.0,
            7.0,
            5.0
        ],
        "q0.5": [
            31.0,
            23.0,
            17.0,
            16.0
        ],
        "q0.75": [
            51.0,
            42.0,
            33.0,
            35.0
        ],
        "q0.975": [
            114.0,
            127.0,
            138.0,
            146.0
        ]
    },
    "CFA_Pyrenew-Pyrenew_HE_Flu": {
        "target_end_date": [
            "2026-04-11",
            "2026-04-18"
        ],
        "q0.025": [
            40.0,
            16.0
        ],
        "q0.25": [
            84.0,
            44.0
        ],
        "q0.5": [
            121.0,
            70.0
        ],
        "q0.75": [
            168.0,
            108.0
        ],
        "q0.975": [
            312.02499999999986,
            246.04999999999973
        ]
    },
    "CU-ensemble": {
        "target_end_date": [
            "2026-04-04",
            "2026-04-11",
            "2026-04-18",
            "2026-04-25",
            "2026-05-02"
        ],
        "q0.025": [
            28.0,
            0.0,
            0.0,
            0.0,
            0.0
        ],
        "q0.25": [
            31.0,
            4.0,
            3.0,
            2.0,
            1.0
        ],
        "q0.5": [
            34.0,
            13.0,
            17.0,
            26.0,
            42.0
        ],
        "q0.75": [
            35.0,
            52.0,
            68.0,
            92.0,
            123.0
        ],
        "q0.975": [
            39.0,
            138.0,
            176.0,
            228.0,
            299.0
        ]
    },
    "CMU-TimeSeries": {
        "target_end_date": [
            "2026-04-04",
            "2026-04-11",
            "2026-04-18",
            "2026-04-25",
            "2026-05-02"
        ],
        "q0.025": [
            31.429351023950577,
            7.9671463240144895,
            3.484768403718793,
            1.0725772425133464,
            1.0791358126938646
        ],
        "q0.25": [
            61.59014973938786,
            22.387030638394755,
            16.470595196631308,
            11.057942190202898,
            8.139756262172574
        ],
        "q0.5": [
            75.94807398678525,
            30.717233957327732,
            25.17997051004071,
            19.688228018979842,
            16.668579941060596
        ],
        "q0.75": [
            96.10353722282886,
            43.065302769384175,
            38.74984517539888,
            35.44647223629714,
            32.0119337569609
        ],
        "q0.975": [
            209.0829429672892,
            100.3921971421618,
            98.47609037283468,
            95.6007234982996,
            104.8039083221966
        ]
    },
    "NAU-FourCAT": {
        "target_end_date": [
            "2026-04-11",
            "2026-04-18",
            "2026-04-25",
            "2026-05-02"
        ],
        "q0.025": [
            0.0,
            0.0,
            0.0,
            0.0
        ],
        "q0.25": [
            0.0,
            0.0,
            0.0,
            0.0
        ],
        "q0.5": [
            0.0,
            0.0,
            0.0,
            0.0
        ],
        "q0.75": [
            19.0,
            0.0,
            0.0,
            0.0
        ],
        "q0.975": [
            108.0,
            86.0,
            70.0,
            72.0
        ]
    },
    "LosAlamos-ThinMint": {
        "target_end_date": [
            "2026-04-04",
            "2026-04-11",
            "2026-04-18",
            "2026-04-25",
            "2026-05-02"
        ],
        "q0.025": [
            0.0,
            0.0,
            0.0,
            0.0,
            0.0
        ],
        "q0.25": [
            0.0,
            0.0,
            0.0,
            0.0,
            0.0
        ],
        "q0.5": [
            35.0,
            0.0,
            0.0,
            0.0,
            0.0
        ],
        "q0.75": [
            102.0,
            0.0,
            0.0,
            0.0,
            0.0
        ],
        "q0.975": [
            301.0,
            118.0,
            224.0,
            228.0,
            241.0
        ]
    },
    "UM-DeepOutbreak": {
        "target_end_date": [
            "2026-04-11",
            "2026-04-18",
            "2026-04-25",
            "2026-05-02"
        ],
        "q0.025": [
            0.0,
            0.0,
            0.0,
            0.0
        ],
        "q0.25": [
            0.0,
            0.0,
            0.0,
            0.0
        ],
        "q0.5": [
            32.97368411666671,
            39.92641328833328,
            39.76470280714111,
            108.13212396779784
        ],
        "q0.75": [
            137.34403083571664,
            163.36980619699324,
            344.2078875492427,
            367.9815753658333
        ],
        "q0.975": [
            915.4987208666662,
            1600.7236818816664,
            2293.9020169041664,
            2367.202641745833
        ]
    },
    "MOBS-GLEAM_RL_FLUH": {
        "target_end_date": [
            "2026-04-11",
            "2026-04-18",
            "2026-04-25",
            "2026-05-02"
        ],
        "q0.025": [
            18.157176971435547,
            12.740030288696287,
            8.719948768615723,
            7.158004283905029
        ],
        "q0.25": [
            25.258033752441406,
            18.78433609008789,
            14.084516525268556,
            12.06668758392334
        ],
        "q0.5": [
            29.55553436279297,
            22.53424835205078,
            17.258094787597656,
            15.206588745117188
        ],
        "q0.75": [
            34.17693328857422,
            26.690738677978516,
            20.993362426757812,
            18.839088439941406
        ],
        "q0.975": [
            44.4156379699707,
            35.53445816040039,
            29.796831130981445,
            27.334693908691406
        ]
    },
    "LosAlamos_NAU-CModel_Flu": {
        "target_end_date": [
            "2026-04-11",
            "2026-04-18",
            "2026-04-25",
            "2026-05-02"
        ],
        "q0.025": [
            47.0,
            36.0,
            28.0,
            22.0
        ],
        "q0.25": [
            69.0,
            54.0,
            42.0,
            34.0
        ],
        "q0.5": [
            83.0,
            65.0,
            51.0,
            41.0
        ],
        "q0.75": [
            98.0,
            78.0,
            62.0,
            50.0
        ],
        "q0.975": [
            132.0,
            106.0,
            84.0,
            68.0
        ]
    },
    "FluSight-trained_mean": {
        "target_end_date": [
            "2026-04-11",
            "2026-04-18",
            "2026-04-25",
            "2026-05-02"
        ],
        "q0.025": [
            3.6719091884568917,
            1.098609752265852,
            0.5389446495329739,
            0.43012995603739484
        ],
        "q0.25": [
            12.703400901801196,
            6.0968308353073475,
            3.6576239887571456,
            2.5464952285304965
        ],
        "q0.5": [
            22.451076621855837,
            16.432293812513286,
            15.083578487310954,
            18.486963726834933
        ],
        "q0.75": [
            43.589125895631675,
            41.69124531478759,
            43.96723570937336,
            50.18611148499405
        ],
        "q0.975": [
            104.66959492399467,
            127.67964445633564,
            151.0259732952106,
            178.2388099362097
        ]
    },
    "CFA_Pyrenew-Pyrenew_H_Flu": {
        "target_end_date": [
            "2026-04-11",
            "2026-04-18"
        ],
        "q0.025": [
            3.0,
            0.0
        ],
        "q0.25": [
            7.0,
            2.0
        ],
        "q0.5": [
            11.0,
            4.0
        ],
        "q0.75": [
            15.0,
            7.0
        ],
        "q0.975": [
            28.0,
            22.0
        ]
    },
    "UGA_flucast-INFLAenza": {
        "target_end_date": [
            "2026-04-11",
            "2026-04-18",
            "2026-04-25",
            "2026-05-02"
        ],
        "q0.025": [
            16.97500000000001,
            11.0,
            9.0,
            7.0
        ],
        "q0.25": [
            27.0,
            23.0,
            19.0,
            16.0
        ],
        "q0.5": [
            36.0,
            32.0,
            28.0,
            24.0
        ],
        "q0.75": [
            45.0,
            43.0,
            40.0,
            36.0
        ],
        "q0.975": [
            69.0,
            74.0,
            75.0,
            74.0
        ]
    },
    "FluSight-trained_med": {
        "target_end_date": [
            "2026-04-11",
            "2026-04-18",
            "2026-04-25",
            "2026-05-02"
        ],
        "q0.025": [
            1.0954563424926342,
            0.0,
            0.0,
            0.0
        ],
        "q0.25": [
            15.028761574595851,
            4.011163179030646,
            4.30498421514695,
            2.0
        ],
        "q0.5": [
            30.856989554711966,
            22.2574484641416,
            16.18107659692965,
            19.58
        ],
        "q0.75": [
            49.125,
            40.374922587699444,
            32.22323611814857,
            34.49716498052561
        ],
        "q0.975": [
            121.32343568927098,
            132.0,
            150.61719775211265,
            150.36719775211265
        ]
    },
    "FluSight-lop_norm": {
        "target_end_date": [
            "2026-04-11",
            "2026-04-18",
            "2026-04-25",
            "2026-05-02"
        ],
        "q0.025": [
            0.0,
            0.0,
            0.0,
            0.0
        ],
        "q0.25": [
            16.0,
            6.0,
            3.0,
            2.0
        ],
        "q0.5": [
            32.0,
            23.0,
            17.0,
            16.0
        ],
        "q0.75": [
            56.0,
            48.0,
            41.0,
            41.0
        ],
        "q0.975": [
            182.0,
            218.0,
            265.0,
            340.0
        ]
    },
    "NEU_ISI-FluBcast": {
        "target_end_date": [
            "2026-04-11",
            "2026-04-18",
            "2026-04-25",
            "2026-05-02"
        ],
        "q0.025": [
            14.0,
            12.0,
            8.0,
            7.0
        ],
        "q0.25": [
            23.0,
            15.0,
            10.0,
            7.0
        ],
        "q0.5": [
            29.0,
            16.0,
            12.0,
            8.0
        ],
        "q0.75": [
            30.0,
            18.0,
            13.0,
            10.0
        ],
        "q0.975": [
            32.0,
            19.0,
            16.0,
            14.0
        ]
    },
    "LosAlamos-DoSiDo": {
        "target_end_date": [
            "2026-04-11",
            "2026-04-18",
            "2026-04-25",
            "2026-05-02"
        ],
        "q0.025": [
            0.0,
            0.0,
            0.0,
            0.0
        ],
        "q0.25": [
            0.0,
            0.0,
            0.0,
            0.0
        ],
        "q0.5": [
            0.0,
            0.0,
            0.0,
            0.0
        ],
        "q0.75": [
            33.0,
            13.0,
            4.0,
            0.0
        ],
        "q0.975": [
            140.0,
            184.0,
            218.0,
            265.0
        ]
    },
    "NEU_ISI-AdaptiveEnsemble": {
        "target_end_date": [
            "2026-04-11",
            "2026-04-18",
            "2026-04-25",
            "2026-05-02"
        ],
        "q0.025": [
            11.0,
            7.0,
            6.0,
            4.0
        ],
        "q0.25": [
            22.0,
            17.0,
            13.0,
            13.0
        ],
        "q0.5": [
            29.0,
            23.0,
            20.0,
            20.0
        ],
        "q0.75": [
            36.0,
            28.0,
            27.0,
            25.0
        ],
        "q0.975": [
            51.0,
            41.0,
            48.0,
            56.0
        ]
    },
    "Gatech-ensemble_prob": {
        "target_end_date": [
            "2026-04-11",
            "2026-04-18",
            "2026-04-25",
            "2026-05-02"
        ],
        "q0.025": [
            0.0,
            0.0,
            0.0,
            0.0
        ],
        "q0.25": [
            15.0,
            7.0,
            1.0,
            0.0
        ],
        "q0.5": [
            31.0,
            26.0,
            15.0,
            15.0
        ],
        "q0.75": [
            53.0,
            57.0,
            49.0,
            55.0
        ],
        "q0.975": [
            111.0,
            149.0,
            166.0,
            202.0
        ]
    },
    "Epistorm-Ensemble_Flu": {
        "target_end_date": [
            "2026-04-11",
            "2026-04-18",
            "2026-04-25",
            "2026-05-02"
        ],
        "q0.025": [
            11.0,
            7.0,
            5.0,
            4.0
        ],
        "q0.25": [
            22.0,
            15.0,
            10.0,
            12.06668758392334
        ],
        "q0.5": [
            29.0,
            16.0,
            16.362153193859296,
            15.206588745117188
        ],
        "q0.75": [
            37.0,
            26.69073867797852,
            22.177110727482155,
            21.0
        ],
        "q0.975": [
            85.54525716001072,
            54.95604981603652,
            48.0,
            56.0
        ]
    },
    "UVAFluX-Ensemble": {
        "target_end_date": [
            "2026-04-11",
            "2026-04-18",
            "2026-04-25",
            "2026-05-02"
        ],
        "q0.025": [
            0.0,
            1.0,
            1.0,
            1.0
        ],
        "q0.25": [
            11.0,
            4.0,
            4.0,
            3.0
        ],
        "q0.5": [
            39.0,
            24.0,
            11.0,
            30.0
        ],
        "q0.75": [
            102.0,
            128.0,
            114.0,
            156.0
        ],
        "q0.975": [
            228.0,
            372.0,
            310.0,
            448.0
        ]
    },
    "SigSci-TSENS": {
        "target_end_date": [
            "2026-04-11",
            "2026-04-18",
            "2026-04-25",
            "2026-05-02"
        ],
        "q0.025": [
            0.0,
            0.0,
            0.0,
            0.0
        ],
        "q0.25": [
            0.0,
            0.0,
            0.0,
            0.0
        ],
        "q0.5": [
            30.0,
            22.0,
            14.0,
            1.0
        ],
        "q0.75": [
            81.0,
            126.0,
            168.0,
            203.0
        ],
        "q0.975": [
            179.0,
            324.0,
            463.0,
            587.0
        ]
    },
    "PSI-PROF": {
        "target_end_date": [
            "2026-04-11",
            "2026-04-18",
            "2026-04-25",
            "2026-05-02"
        ],
        "q0.025": [
            0.0,
            0.0,
            0.0,
            0.0
        ],
        "q0.25": [
            31.71,
            22.0,
            15.0,
            10.0
        ],
        "q0.5": [
            40.0,
            38.0,
            33.0,
            26.5
        ],
        "q0.75": [
            73.0,
            69.38,
            66.71,
            68.0
        ],
        "q0.975": [
            294.92,
            472.3,
            603.96,
            665.16
        ]
    },
    "UMass-AR2": {
        "target_end_date": [
            "2026-04-11",
            "2026-04-18",
            "2026-04-25",
            "2026-05-02"
        ],
        "q0.025": [
            0.0,
            0.0,
            0.0,
            0.0
        ],
        "q0.25": [
            9.967024791316137,
            3.198091522332289,
            0.05019697426945966,
            0.0
        ],
        "q0.5": [
            29.96703245130644,
            32.923874396078695,
            37.66330263470604,
            44.59507247631585
        ],
        "q0.75": [
            53.80324616369602,
            79.87327166134209,
            102.14395302017782,
            125.4841694246837
        ],
        "q0.975": [
            120.38535793492488,
            216.41450684670735,
            323.7634656438009,
            453.5373024747882
        ]
    },
    "UMass-flusion": {
        "target_end_date": [
            "2026-04-11",
            "2026-04-18",
            "2026-04-25",
            "2026-05-02"
        ],
        "q0.025": [
            0.641710673505875,
            0.0,
            0.0,
            0.0
        ],
        "q0.25": [
            14.0575231491917,
            6.25448566813328,
            0.994907325011659,
            0.0
        ],
        "q0.5": [
            27.0160834666517,
            20.5148969282832,
            15.2730068825458,
            12.0984465768768
        ],
        "q0.75": [
            36.3394551427692,
            31.4505067523684,
            26.7726322427808,
            24.8369316308044
        ],
        "q0.975": [
            64.1523351523856,
            64.0468578212357,
            63.6359200525312,
            64.0429139548553
        ]
    },
    "LUcompUncertLab-puca": {
        "target_end_date": [
            "2026-04-11",
            "2026-04-18",
            "2026-04-25",
            "2026-05-02"
        ],
        "q0.025": [
            0.0,
            0.0,
            0.0,
            0.0
        ],
        "q0.25": [
            15.0,
            0.0,
            0.0,
            0.0
        ],
        "q0.5": [
            74.0,
            47.0,
            32.0,
            9.0
        ],
        "q0.75": [
            129.0,
            108.0,
            82.0,
            70.0
        ],
        "q0.975": [
            252.0,
            221.0,
            197.0,
            173.0
        ]
    },
    "FluSight-baseline": {
        "target_end_date": [
            "2026-04-04",
            "2026-04-11",
            "2026-04-18",
            "2026-04-25",
            "2026-05-02"
        ],
        "q0.025": [
            33.0,
            0.0,
            0.0,
            0.0,
            0.0
        ],
        "q0.25": [
            33.0,
            17.0,
            0.0,
            0.0,
            0.0
        ],
        "q0.5": [
            33.0,
            33.0,
            33.0,
            33.0,
            33.0
        ],
        "q0.75": [
            33.0,
            49.0,
            109.0,
            169.0,
            218.0
        ],
        "q0.975": [
            33.0,
            595.0,
            710.0,
            788.0,
            855.0
        ]
    },
    "Google_SAI-FluEns": {
        "target_end_date": [
            "2026-04-11",
            "2026-04-18",
            "2026-04-25",
            "2026-05-02"
        ],
        "q0.025": [
            8.6,
            8.2,
            6.8,
            3.8950000000000005
        ],
        "q0.25": [
            20.35,
            18.4,
            15.2,
            12.2
        ],
        "q0.5": [
            33.6,
            29.8,
            26.4,
            23.4
        ],
        "q0.75": [
            56.65,
            52.4,
            52.2,
            50.6
        ],
        "q0.975": [
            181.16499999999968,
            195.60499999999996,
            214.53499999999994,
            221.55999999999977
        ]
    },
    "UGA_CEID-auto_AVG_LB": {
        "target_end_date": [
            "2026-04-11",
            "2026-04-18",
            "2026-04-25",
            "2026-05-02"
        ],
        "q0.025": [
            17.827780744345805,
            18.345447235032143,
            18.345447235032143,
            18.345447235032143
        ],
        "q0.25": [
            33.42077332122937,
            36.257984762434646,
            36.257984762434646,
            36.257984762434646
        ],
        "q0.5": [
            46.471551516885484,
            51.83426017337535,
            51.83426017337535,
            51.83426017337535
        ],
        "q0.75": [
            64.6209041539857,
            74.10484510123756,
            74.10484510123756,
            74.10484510123756
        ],
        "q0.975": [
            121.33462638724902,
            146.71439550422528,
            146.71439550422528,
            146.71439550422528
        ]
    },
    "PSI-PROF_MOA": {
        "target_end_date": [
            "2026-04-11",
            "2026-04-18",
            "2026-04-25",
            "2026-05-02"
        ],
        "q0.025": [
            0.0,
            0.0,
            0.0,
            0.0
        ],
        "q0.25": [
            0.0,
            0.0,
            0.0,
            0.0
        ],
        "q0.5": [
            16.0,
            4.0,
            0.0,
            0.0
        ],
        "q0.75": [
            46.25,
            28.0,
            18.0,
            15.0
        ],
        "q0.975": [
            181.0,
            137.0,
            119.0,
            154.02
        ]
    },
    "UNC_IDD-InfluPaint": {
        "target_end_date": [
            "2026-04-11",
            "2026-04-18",
            "2026-04-25",
            "2026-05-02"
        ],
        "q0.025": [
            5.415070083774154,
            4.003330092836177,
            3.291414775072118,
            2.5765933736701685
        ],
        "q0.25": [
            20.4160693906462,
            16.787854390368842,
            20.48847841250202,
            19.24250213742898
        ],
        "q0.5": [
            31.6498163174774,
            33.76342999413466,
            40.79686363640893,
            46.6136423413986
        ],
        "q0.75": [
            50.73623001527758,
            60.71577332807824,
            81.59987632187531,
            94.38048812781939
        ],
        "q0.975": [
            106.9255288488294,
            167.3640488639668,
            217.6649161935709,
            271.0699733874154
        ]
    },
    "CU-ARNB_Net": {
        "target_end_date": [
            "2026-04-11",
            "2026-04-18",
            "2026-04-25",
            "2026-05-02"
        ],
        "q0.025": [
            0.0,
            0.0,
            0.0,
            0.0
        ],
        "q0.25": [
            8.0,
            6.0,
            4.0,
            3.0
        ],
        "q0.5": [
            19.0,
            15.0,
            10.0,
            8.0
        ],
        "q0.75": [
            39.0,
            30.0,
            21.0,
            17.0
        ],
        "q0.975": [
            104.0,
            80.0,
            58.0,
            47.0
        ]
    },
    "UGA_CEID-Walk": {
        "target_end_date": [
            "2026-04-11",
            "2026-04-18",
            "2026-04-25",
            "2026-05-02"
        ],
        "q0.025": [
            0.0,
            0.0,
            0.0,
            0.0
        ],
        "q0.25": [
            0.0,
            0.0,
            0.0,
            0.0
        ],
        "q0.5": [
            39.959,
            63.332,
            57.431,
            55.649
        ],
        "q0.75": [
            113.647,
            169.706,
            189.205,
            201.77
        ],
        "q0.975": [
            280.029,
            369.793,
            511.689,
            516.262
        ]
    },
    "UGA_flucast-Scenariocast": {
        "target_end_date": [
            "2026-04-11",
            "2026-04-18",
            "2026-04-25",
            "2026-05-02"
        ],
        "q0.025": [
            12.0,
            7.0,
            4.0,
            2.0
        ],
        "q0.25": [
            21.0,
            16.0,
            12.0,
            10.0
        ],
        "q0.5": [
            27.0,
            22.0,
            19.0,
            17.0
        ],
        "q0.75": [
            32.0,
            30.0,
            28.0,
            27.0
        ],
        "q0.975": [
            51.0,
            58.0,
            62.0,
            67.0
        ]
    },
    "Cornell_JHU-hierarchSIR": {
        "target_end_date": [
            "2026-04-04",
            "2026-04-11",
            "2026-04-18",
            "2026-04-25",
            "2026-05-02"
        ],
        "q0.025": [
            21.0,
            14.0,
            0.0,
            0.0,
            0.0
        ],
        "q0.25": [
            49.0,
            28.0,
            14.0,
            7.0,
            0.0
        ],
        "q0.5": [
            70.0,
            42.0,
            28.0,
            14.0,
            7.0
        ],
        "q0.75": [
            91.0,
            63.0,
            42.0,
            21.0,
            14.0
        ],
        "q0.975": [
            133.0,
            105.0,
            70.0,
            42.0,
            28.0
        ]
    },
    "Gatech-ensemble_stat": {
        "target_end_date": [
            "2026-04-11",
            "2026-04-18",
            "2026-04-25",
            "2026-05-02"
        ],
        "q0.025": [
            0.003651801421346992,
            0.0,
            0.0,
            0.0
        ],
        "q0.25": [
            13.485883418006203,
            0.0,
            0.0,
            0.0
        ],
        "q0.5": [
            30.9967451520962,
            0.0,
            0.0,
            0.0
        ],
        "q0.75": [
            55.69086195172244,
            14.065082768762865,
            24.248423956310102,
            32.994329961051214
        ],
        "q0.975": [
            122.64486001892536,
            118.76480650936148,
            204.75239475476195,
            278.6023572099423
        ]
    },
    "OHT_JHU-nbxd": {
        "target_end_date": [
            "2026-04-11",
            "2026-04-18",
            "2026-04-25",
            "2026-05-02"
        ],
        "q0.025": [
            10.26,
            2.9,
            1.85,
            1.48
        ],
        "q0.25": [
            28.69,
            14.2,
            11.33,
            9.81
        ],
        "q0.5": [
            46.35,
            28.69,
            24.87,
            22.16
        ],
        "q0.75": [
            72.3,
            53.89,
            49.92,
            45.48
        ],
        "q0.975": [
            155.01,
            152.08,
            154.52,
            145.12
        ]
    },
    "NAU-vulPES": {
        "target_end_date": [
            "2026-04-11",
            "2026-04-18",
            "2026-04-25",
            "2026-05-02"
        ],
        "q0.025": [
            9.0,
            6.0,
            4.0,
            2.0
        ],
        "q0.25": [
            16.0,
            13.0,
            10.0,
            8.0
        ],
        "q0.5": [
            22.0,
            18.0,
            16.0,
            14.0
        ],
        "q0.75": [
            32.0,
            25.0,
            23.0,
            22.0
        ],
        "q0.975": [
            71.0,
            68.0,
            65.0,
            68.0
        ]
    },
    "MIGHTE-Joint": {
        "target_end_date": [
            "2026-04-11",
            "2026-04-18",
            "2026-04-25",
            "2026-05-02"
        ],
        "q0.025": [
            1.5492020114793934,
            0.0,
            0.0,
            0.0
        ],
        "q0.25": [
            16.709969103124802,
            4.022326358061291,
            4.609968430293901,
            12.184692433674783
        ],
        "q0.5": [
            28.036711722786187,
            15.762131279973145,
            16.362153193859296,
            29.97554871656484
        ],
        "q0.75": [
            45.985101491976835,
            42.82044844951425,
            44.11083303985807,
            92.70810175798049
        ],
        "q0.975": [
            121.31224499129293,
            255.07864278474617,
            397.3291332209705,
            654.2381867661983
        ]
    },
    "UGA_flucast-Copycat": {
        "target_end_date": [
            "2026-04-11",
            "2026-04-18",
            "2026-04-25",
            "2026-05-02"
        ],
        "q0.025": [
            8.0,
            4.0,
            1.0,
            0.0
        ],
        "q0.25": [
            17.0,
            12.0,
            8.0,
            6.0
        ],
        "q0.5": [
            24.0,
            19.0,
            16.0,
            14.0
        ],
        "q0.75": [
            32.0,
            27.0,
            25.0,
            25.0
        ],
        "q0.975": [
            55.0,
            52.0,
            53.0,
            58.0
        ]
    },
    "MOBS-EpyStrain_Flu": {
        "target_end_date": [
            "2026-04-04",
            "2026-04-11",
            "2026-04-18",
            "2026-04-25",
            "2026-05-02"
        ],
        "q0.025": [
            30.0,
            17.0,
            8.0,
            5.0,
            4.0
        ],
        "q0.25": [
            53.0,
            31.0,
            18.0,
            13.0,
            10.0
        ],
        "q0.5": [
            72.0,
            43.0,
            26.0,
            18.0,
            15.0
        ],
        "q0.75": [
            99.0,
            60.0,
            37.0,
            26.0,
            21.0
        ],
        "q0.975": [
            156.0,
            114.0,
            69.0,
            50.0,
            38.0
        ]
    },
    "VTSanghani-PRIME": {
        "target_end_date": [
            "2026-04-04",
            "2026-04-11",
            "2026-04-18",
            "2026-04-25",
            "2026-05-02"
        ],
        "q0.025": [
            0.0,
            4.0,
            9.0,
            12.0,
            12.0
        ],
        "q0.25": [
            13.0,
            81.0,
            181.0,
            246.0,
            252.0
        ],
        "q0.5": [
            33.0,
            191.0,
            425.0,
            577.0,
            591.0
        ],
        "q0.75": [
            52.0,
            301.0,
            669.0,
            907.0,
            929.0
        ],
        "q0.975": [
            67.0,
            379.0,
            842.0,
            1142.0,
            1169.0
        ]
    },
    "UMass-trends_ensemble": {
        "target_end_date": [
            "2026-04-11",
            "2026-04-18",
            "2026-04-25",
            "2026-05-02"
        ],
        "q0.025": [
            0.0,
            0.0,
            0.0,
            0.0
        ],
        "q0.25": [
            0.0,
            0.0,
            0.0,
            0.0
        ],
        "q0.5": [
            19.5,
            16.5,
            16.5,
            16.5
        ],
        "q0.75": [
            43.0,
            46.5,
            55.5,
            63.0
        ],
        "q0.975": [
            100.5,
            140.0,
            182.5,
            228.0
        ]
    },
    "CEPH-Rtrend_fluH": {
        "target_end_date": [
            "2026-04-11",
            "2026-04-18",
            "2026-04-25",
            "2026-05-02"
        ],
        "q0.025": [
            4.0,
            0.0,
            0.0,
            0.0
        ],
        "q0.25": [
            13.0,
            1.0,
            0.0,
            0.0
        ],
        "q0.5": [
            23.0,
            8.0,
            1.0,
            0.0
        ],
        "q0.75": [
            37.0,
            24.0,
            13.0,
            6.0
        ],
        "q0.975": [
            86.0,
            127.0,
            156.0,
            168.0
        ]
    },
    "NIH-Flu_ARIMA": {
        "target_end_date": [
            "2026-04-11",
            "2026-04-18",
            "2026-04-25",
            "2026-05-02"
        ],
        "q0.025": [
            9.0,
            5.0,
            1.0,
            0.0
        ],
        "q0.25": [
            18.0,
            16.0,
            7.0,
            4.0
        ],
        "q0.5": [
            21.0,
            23.0,
            14.0,
            10.0
        ],
        "q0.75": [
            25.0,
            34.0,
            25.0,
            20.0
        ],
        "q0.975": [
            41.0,
            70.0,
            80.0,
            84.0
        ]
    }
}